pheasant/__init__.py
pheasant/main.py
pheasant/app/__init__.py
pheasant/app/app.py
pheasant/core/__init__.py
pheasant/core/base.py
pheasant/core/converter.py
pheasant/core/decorator.py
pheasant/core/page.py
pheasant/core/parser.py
pheasant/core/pheasant.py
pheasant/core/renderer.py
pheasant/plugins/__init__.py
pheasant/plugins/mkdocs.py
pheasant/renderers/__init__.py
pheasant/renderers/embed/__init__.py
pheasant/renderers/embed/embed.py
pheasant/renderers/embed/templates/fenced_code.jinja2
pheasant/renderers/jupyter/__init__.py
pheasant/renderers/jupyter/filters.py
pheasant/renderers/jupyter/ipython.py
pheasant/renderers/jupyter/jupyter.py
pheasant/renderers/jupyter/kernel.py
pheasant/renderers/jupyter/templates/fenced_code.jinja2
pheasant/renderers/jupyter/templates/inline_code.jinja2
pheasant/renderers/jupyter/templates/macro.jinja2
pheasant/renderers/number/__init__.py
pheasant/renderers/number/number.py
pheasant/renderers/number/templates/anchor.jinja2
pheasant/renderers/number/templates/base.jinja2
pheasant/renderers/number/templates/header.jinja2
pheasant/renderers/script/__init__.py
pheasant/renderers/script/formatter.py
pheasant/renderers/script/script.py
pheasant/renderers/script/splitter.py
pheasant/theme/pheasant.yml
pheasant/theme/css/pheasant.css
pheasant/theme/js/pheasant.js
pheasant/utils/__init__.py
pheasant/utils/progress.py
pheasant/utils/time.py
pheasant-2.5.9.dist-info/LICENSE
pheasant-2.5.9.dist-info/METADATA
pheasant-2.5.9.dist-info/WHEEL
pheasant-2.5.9.dist-info/entry_points.txt
pheasant-2.5.9.dist-info/top_level.txt
pheasant-2.5.9.dist-info/RECORD
